setup.py
pyimq/__init__.py
pyimq/filters.py
pyimq/myimage.py
pyimq/script_options.py
pyimq/utils.py
pyimq.egg-info/PKG-INFO
pyimq.egg-info/SOURCES.txt
pyimq.egg-info/dependency_links.txt
pyimq.egg-info/entry_points.txt
pyimq.egg-info/requires.txt
pyimq.egg-info/top_level.txt
pyimq/bin/__init__.py
pyimq/bin/extract_channel.py
pyimq/bin/image_subtractor.py
pyimq/bin/main.py
pyimq/bin/power.py
pyimq/bin/subjective.py
pyimq/bin/test/__init__.py
pyimq/bin/test/test_resolution_filter.py
pyimq/bin/test/test_rgb_channel_select.py
pyimq/bin/utils/__init__.py
pyimq/bin/utils/create_blur_sequence.py
pyimq/bin/utils/create_photo_test_set.py
pyimq/external/__init__.py
pyimq/external/radial_profile.py